nango/__init__.py
nango/admin.py
nango/apps.py
nango/common.py
nango/consumers.py
nango/routing.py
nango/tests.py
nango/views.py
nango/contrib/__init__.py
nango/contrib/admin/__init__.py
nango/contrib/admin/admin.py
nango/contrib/admin/site.py
nango/db/__init__.py
nango/db/models.py
nango/forms/__init__.py
nango/migrations/__init__.py
nango/static/nango/admin.js
nango/static/nango/ws.css
nango/static/nango/ws.js
nango/views/__init__.py
nango/views/generic/__init__.py
nango/views/generic/edit.py
nango-0.1.2.dist-info/METADATA
nango-0.1.2.dist-info/WHEEL
nango-0.1.2.dist-info/top_level.txt
nango-0.1.2.dist-info/RECORD
