Metadata-Version: 2.1
Name: nango
Version: 0.1.2
Summary: Provide model integrity between requests
Home-page: https://github.com/nicois/nango
Author: Nick Farrell
Author-email: nicholas.farrell@gmail.com
License: UNKNOWN
Project-URL: Bug Tracker, https://github.com/nicois/nango/issues
Platform: UNKNOWN
Classifier: Programming Language :: Python :: 3
Classifier: License :: OSI Approved :: MIT License
Classifier: Operating System :: OS Independent
Requires-Python: >=3.8
